tiblombok/__init__.py
tiblombok/common.py
tiblombok/tiblombok.py
tiblombok-0.0.1.dist-info/LICENSE
tiblombok-0.0.1.dist-info/METADATA
tiblombok-0.0.1.dist-info/WHEEL
tiblombok-0.0.1.dist-info/entry_points.txt
tiblombok-0.0.1.dist-info/top_level.txt
tiblombok-0.0.1.dist-info/RECORD
